tempest_lib/__init__.py
tempest_lib/base.py
tempest_lib/exceptions.py
tempest_lib/decorators.py
tempest_lib/auth.py
tempest_lib/cli/__init__.py
tempest_lib/cli/base.py
tempest_lib/cli/output_parser.py
tempest_lib/api_schema/__init__.py
tempest_lib/api_schema/response/__init__.py
tempest_lib/api_schema/response/compute/__init__.py
tempest_lib/api_schema/response/compute/v2_1/hypervisors.py
tempest_lib/api_schema/response/compute/v2_1/__init__.py
tempest_lib/api_schema/response/compute/v2_1/quota_classes.py
tempest_lib/api_schema/response/compute/v2_1/services.py
tempest_lib/api_schema/response/compute/v2_1/interfaces.py
tempest_lib/api_schema/response/compute/v2_1/fixed_ips.py
tempest_lib/api_schema/response/compute/v2_1/hosts.py
tempest_lib/api_schema/response/compute/v2_1/availability_zone.py
tempest_lib/api_schema/response/compute/v2_1/certificates.py
tempest_lib/api_schema/response/compute/v2_1/security_group_default_rule.py
tempest_lib/api_schema/response/compute/v2_1/floating_ips.py
tempest_lib/api_schema/response/compute/v2_1/tenant_networks.py
tempest_lib/api_schema/response/compute/v2_1/security_groups.py
tempest_lib/api_schema/response/compute/v2_1/migrations.py
tempest_lib/api_schema/response/compute/v2_1/baremetal_nodes.py
tempest_lib/api_schema/response/compute/v2_1/servers.py
tempest_lib/api_schema/response/compute/v2_1/agents.py
tempest_lib/api_schema/response/compute/v2_1/images.py
tempest_lib/api_schema/response/compute/v2_1/keypairs.py
tempest_lib/api_schema/response/compute/v2_1/quotas.py
tempest_lib/api_schema/response/compute/v2_1/flavors.py
tempest_lib/api_schema/response/compute/v2_1/flavors_extra_specs.py
tempest_lib/api_schema/response/compute/v2_1/aggregates.py
tempest_lib/api_schema/response/compute/v2_1/snapshots.py
tempest_lib/api_schema/response/compute/v2_1/instance_usage_audit_logs.py
tempest_lib/api_schema/response/compute/v2_1/volumes.py
tempest_lib/api_schema/response/compute/v2_1/limits.py
tempest_lib-1.0.0.dist-info/METADATA
tempest_lib-1.0.0.dist-info/top_level.txt
tempest_lib-1.0.0.dist-info/entry_points.txt
tempest_lib-1.0.0.dist-info/pbr.json
tempest_lib-1.0.0.dist-info/RECORD
tempest_lib-1.0.0.dist-info/DESCRIPTION.rst
tempest_lib-1.0.0.dist-info/metadata.json
tempest_lib-1.0.0.dist-info/WHEEL
